refrakt_core/__init__.py
refrakt_core/datasets.py
refrakt_core/error_handling.py
refrakt_core/global_logging.py
refrakt_core/logging_config.py
refrakt_core/transforms.py
refrakt_core/api/__init__.py
refrakt_core/api/inference.py
refrakt_core/api/test.py
refrakt_core/api/train.py
refrakt_core/api/builders/__init__.py
refrakt_core/api/builders/dataloader_builder.py
refrakt_core/api/builders/dataset_builder.py
refrakt_core/api/builders/loss_builder.py
refrakt_core/api/builders/model_builder.py
refrakt_core/api/builders/optimizer_builder.py
refrakt_core/api/builders/scheduler_builder.py
refrakt_core/api/builders/trainer_builder.py
refrakt_core/api/builders/transform_builder.py
refrakt_core/api/builders/utils/__init__.py
refrakt_core/api/builders/utils/loss_utils.py
refrakt_core/api/builders/utils/model_utils.py
refrakt_core/api/builders/utils/optimizer_utils.py
refrakt_core/api/builders/utils/trainer_utils.py
refrakt_core/api/builders/utils/transform_utils.py
refrakt_core/api/core/__init__.py
refrakt_core/api/core/components.py
refrakt_core/api/core/extras.py
refrakt_core/api/core/logger.py
refrakt_core/api/core/utils/__init__.py
refrakt_core/api/core/utils/logger_helpers.py
refrakt_core/api/core/utils/logging_utils.py
refrakt_core/api/helpers/__init__.py
refrakt_core/api/helpers/image_analysis_helpers.py
refrakt_core/api/helpers/inference_helpers.py
refrakt_core/api/helpers/test_helpers.py
refrakt_core/api/helpers/train_helpers.py
refrakt_core/api/utils/__init__.py
refrakt_core/api/utils/hooks_orchestrator.py
refrakt_core/api/utils/image_analysis_utils.py
refrakt_core/api/utils/inference_utils.py
refrakt_core/api/utils/pipeline_utils.py
refrakt_core/api/utils/test_utils.py
refrakt_core/api/utils/train_utils.py
refrakt_core/config/ae.yaml
refrakt_core/config/convnext.yaml
refrakt_core/config/dino.yaml
refrakt_core/config/mae.yaml
refrakt_core/config/msn.yaml
refrakt_core/config/resnet.yaml
refrakt_core/config/simclr.yaml
refrakt_core/config/vit.yaml
refrakt_core-0.4.0.dist-info/licenses/LICENSE
refrakt_core-0.4.0.dist-info/METADATA
refrakt_core-0.4.0.dist-info/WHEEL
refrakt_core-0.4.0.dist-info/top_level.txt
refrakt_core-0.4.0.dist-info/RECORD
