Metadata-Version: 2.4
Name: refrakt_core
Version: 0.4.0
Summary: Core ML/DL training library for Refrakt framework
Author-email: Akshath Mangudi <akshathmangudi@gmail.com>
License: MIT License
Project-URL: Homepage, https://github.com/refrakt-hub/refrakt_core
Project-URL: Bug Tracker, https://github.com/refrakt-hub/refrakt_core/issues
Requires-Python: >=3.10
License-File: LICENSE
Requires-Dist: torch>=2.0
Requires-Dist: torchvision
Requires-Dist: einops
Requires-Dist: matplotlib
Requires-Dist: numpy
Requires-Dist: requests
Requires-Dist: pillow
Requires-Dist: pandas
Requires-Dist: tqdm
Requires-Dist: omegaconf
Requires-Dist: timm
Requires-Dist: pydantic
Requires-Dist: scikit-learn
Requires-Dist: xgboost
Provides-Extra: dev
Requires-Dist: pytest>=7.0.0; extra == "dev"
Requires-Dist: pytest-cov>=4.0.0; extra == "dev"
Requires-Dist: black>=23.0.0; extra == "dev"
Requires-Dist: ruff>=0.1.0; extra == "dev"
Requires-Dist: isort>=5.12.0; extra == "dev"
Requires-Dist: mypy>=1.0.0; extra == "dev"
Requires-Dist: pre-commit>=3.0.0; extra == "dev"
Requires-Dist: types-requests>=2.28.0; extra == "dev"
Requires-Dist: types-PyYAML>=6.0.0; extra == "dev"
Requires-Dist: pandas-stubs>=1.5.0; extra == "dev"
Requires-Dist: types-pytz>=2022.1.0; extra == "dev"
Requires-Dist: types-tqdm>=4.64.0; extra == "dev"
Requires-Dist: typing-extensions>=4.0.0; extra == "dev"
Requires-Dist: radon>=6.0.0; extra == "dev"
Requires-Dist: lizard>=1.17.10; extra == "dev"
Dynamic: license-file
